[
{"title": "통통생굴 2kg / 횟감용 10%쿠폰 최대혜택가 19380원", "price": "21,900원"},
{"title": "[닥터방기원]랩 탈모샴푸 1Lx3통+랩토닉 150ml+싱글파우치+폼클렌징", "price": "27,900원"},
{"title": "무농약 베니하루카 해남 꿀고구마 3kg 특상(120~290g)", "price": "20,280원"},
{"title": "[피지오겔]피지오겔 DMT 로션 200ml", "price": "21,900원"},
{"title": "[탑텐키즈](대구신세계)[탑텐키즈] 20FW 신상 아동 온에어세트", "price": "5,610원"},
{"title": "[CJ고메]고메 함박 스테이크 152g x10개 (냉장)", "price": "20,300원"},
{"title": "[센텔리안24]센텔리안24 마데카크림 파워 부스팅 포뮬러 50mlX2개", "price": "24,000원"},
{"title": "[매일유업]매일두유 검은콩 식물성단백질 두유 190ml 24팩", "price": "9,900원"},
{"title": "[파스퇴르]파스퇴르 무항생제 인증 바른목장(190ml48입)/멸균우유", "price": "25,960원"},
{"title": "[쵱선생]국내산 조림 볶음용 지리 멸치 1kg/ 10290원 12%쿠폰가", "price": "11,900원"},
{"title": "[얌테이블]통영 자연산 돌문어 (생물)1kg/10%쿠폰가 22090원", "price": "24,900원"},
{"title": "월튼키즈/파격균일가/겨울클리어런스/아동복/아우터外", "price": "9,900원"},
{"title": "(화이트샌즈) 니트 보닛햇_블랙", "price": "26,400원"},
{"title": "(삼진어묵) 옛날모듬어묵 1Kg x 3개", "price": "24,900원"},
{"title": "[게스]25%중복 GUESS 겨울 세일전", "price": "39,000원"},
{"title": "[한성]반찬/ 한성 프리미엄 해물경단 (270g+270g x 3P)", "price": "22,500원"},
{"title": "[키즈마루]국산 3중 비말차단 마스크  300매 KF-AD MB필터 마스크", "price": "17,900원"},
{"title": "[폴햄][폴햄]남/녀 핫스킨 발열내의 1+1 4종 택1", "price": "9,120원"},
{"title": "구석구석 숨어있는 그림속 이야기 5권 세트 (전5권)", "price": "22,520원"},
{"title": "2020 하지감자 수미감자 5kg  특(140g 이상)", "price": "9,500원"},
{"title": "[폴햄]남여 그래픽 플리스 맨투맨 4종택1(PHA4TR3020 PHA4TR1200 PHA4TR2020 PHA4TR2030)", "price": "12,290원"},
{"title": "맛있는 조생 감귤 5kg(2S-M/로얄랜덤)/2개구매15kg발송", "price": "6,900원"},
{"title": "[올곧은]캡형  70매 엠보싱 10팩_Z503", "price": "17,520원"},
{"title": "태송 프리미엄 다섯가지나물밥 210g x10봉", "price": "16,400원"},
{"title": "[풀무원]풀무원 토이쿠키 만들기 3종 세트(총3박스)", "price": "28,900원"},
{"title": "서래푸드 3.75kg관볶음땅콩 무료배송", "price": "18,500원"},
{"title": "[김정문알로에]김정문알로에 스킨케어 기획세트 추가할인+증정", "price": "26,500원"},
{"title": "[애경]주방세제 순샘 대용량 3L x4개(베리2+라임2)+사은품", "price": "14,900원"},
{"title": "[아임닭]하루만무배/한입스팀 닭가슴살 100g 5팩외 BEST50종", "price": "7,900원"},
{"title": "[오뚜기밥]맛있는 오뚜기밥 210g 24개", "price": "19,900원"},
{"title": "[디스커버리](여성) 티롤린 벤치 롱 다운 DWDJ96961", "price": "163,240원"},
{"title": "[페리오]치약 뉴후레쉬 알파치약 170g 10+10개", "price": "14,900원"},
{"title": "[팬콧키즈]25%쿠폰 패딩 플리스 기모 티셔츠 팬츠 상하복 바지", "price": "22,900원"},
{"title": "센스물티슈 악어 캡형 100매 10팩+10팩 / 한장씩톡톡", "price": "16,900원"},
{"title": "경성명과 1+1 수제 케이크 롤+ 다크파운드", "price": "10,900원"},
{"title": "밥상마루 100% 참기름 350ml 1+1", "price": "17,900원"},
{"title": "[2080]2080 치약 히말라야 솔트치약 120gx15개(크리스탈15)", "price": "12,900원"},
{"title": "프라이데이 겨울신상 기모맨투맨/후드티/빅사이즈", "price": "11,900원"},
{"title": "[참도깨비]삼겹살 구이 수육 보쌈/ 벌집통삼겹살 500g x2봉/ 1kg", "price": "11,900원"},
{"title": "시스터 기모신상~ 빅사이즈롱티/롱후드/롱원피스/세트", "price": "5,900원"},
{"title": "[기린]호빵 팥(8입)+야채(4입)+피자(4입) 총16입", "price": "12,900원"},
{"title": "사미헌 갈비탕1kg  5팩", "price": "55,000원"},
{"title": "찹쌀 모싯잎 오쟁이 떡  1.2kg (40g x 30개)", "price": "11,900원"},
{"title": "[순수한면](골라담기)순수한면 ZERO 생리대 x 3+3팩", "price": "16,000원"},
{"title": "48시간 과일숙성 돼지 생막창 2KG 도매 식당납품용", "price": "32,900원"},
{"title": "[쉬즈홈]쾌적하고 산뜻힌 매트리스커버", "price": "9,900원"},
{"title": "[AK기획]IVOW 충전식 무선 온수찜질기 CES-H01", "price": "18,220원"},
{"title": "밀크앤허니 베이커리 1+1 골라담기 (신세계푸드)", "price": "12,900원"},
{"title": "투투 겨울신상 기모 슬랙스/청바지/배기/골덴 5XL", "price": "9,900원"},
{"title": "[키스포]주니어 겨울마감가 7900~ 1+1특가 양털자켓 방한내의", "price": "8,900원"},
{"title": "[하누소]하누소 왕갈비탕(650g6팩)", "price": "34,700원"},
{"title": "[한예지]한예지 볼륨앤소프트 천연펄프 3겹  화장지 30롤 3팩", "price": "26,900원"},
{"title": "J by 20FW 클라우드 헤비 부클니트 3종", "price": "49,000원"},
{"title": "제주 감귤 타이벡 10kg내외 (L-2L)", "price": "7,900원"},
{"title": "[아침농산]수입 귀리 10kg(5kg+5kg) 캐나다산 2020년산", "price": "11,500원"},
{"title": "[모노블랙]모노블랙 T 겨울 맨투맨 4900원부터 원피스 점퍼 5", "price": "7,900원"},
{"title": "런칭가 69 900원 코펜하겐럭스 기모 밴딩팬츠 4종", "price": "39,900원"},
{"title": "[해태제과]맛동산 38g x 22팩", "price": "10,900원"},
{"title": "라이프케어 멀티 생 유산균 라이브 300포+유산균 증정", "price": "41,700원"},
{"title": "[롯데푸드]매콤오징어롤x2팩+쫄깃롤만두x2팩 /2팩씩(총 4팩)", "price": "9,900원"},
{"title": "자연 모짜렐라 슈레드치즈 1kg  /피자치즈/대용량", "price": "11,900원"},
{"title": "[피지오겔]피지오겔 DMT 로션 200ml 2개 +증정", "price": "43,800원"},
{"title": "[육개장]육개장사발면 24개입 박스 스마일배송", "price": "15,900원"},
{"title": "[이지바이]균일가 7900원 32종/기모티/패딩/바지/조끼/후리스", "price": "7,900원"},
{"title": "KF94 국산 마스크 100매 식약처인증 의약외품 개별포장", "price": "27,900원"},
{"title": "[의성마늘햄]롯데 의성마늘 프랑크 70gx20개", "price": "13,900원"},
{"title": "[퐁퐁]퐁퐁 주방세제 레몬식초 3000ML  4개", "price": "18,900원"},
{"title": "[대천김][대천김] 재래 도시락김 총 160봉", "price": "35,910원"},
{"title": "[롯데푸드]라퀴진 큐브감자핫도그 90gx10개", "price": "14,900원"},
{"title": "[깨끗한나라]순수브라운 3겹 화장지 27m 30롤 2팩", "price": "24,800원"},
{"title": "[아이시스]아이시스 8.0 300ml 40펫", "price": "8,900원"},
{"title": "[리큐]액체세탁세제 리큐 알카파워2.1Lx6개(일반용)", "price": "18,900원"},
{"title": "[생활공작소]친환경 1종 대용량 주방세제 4L x 2개 (향 선택)", "price": "12,900원"},
{"title": "이베이 전용 남순남순대국 10인분 풀세트", "price": "36,900원"},
{"title": "HAPPYDAY 핫팩 군용60매/포켓100매/파스형90매", "price": "23,780원"},
{"title": "[에쓰오일](S-OIL) 모바일주유권 5만원/ 실시간발송/ 주유상품권", "price": "49,000원"},
{"title": "마이비밀  즐거운 식단관리 라이킷 도시락 10종 10팩 外", "price": "29,900원"},
{"title": "[김영사]출판사 연합유주맘 pick 육아서 7종 낱권 선택구매", "price": "18,480원"},
{"title": "[잘풀리는집]미래생활 순수PURE천연펄프 25m 30롤 x 3팩", "price": "23,900원"},
{"title": "[서울우유]서울우유 1000ml X 10팩/멸균우유/흰우유", "price": "18,500원"},
{"title": "[프로쉬]독일 친환경 식기세척기세제 베이킹소다 2개SET  60EA", "price": "22,900원"},
{"title": "코크제로 355ml캔 24입/ 코카콜라", "price": "18,610원"},
{"title": "[맥심]화이트골드 커피믹스 160Tx2 /쿠폰적용가29190원", "price": "32,900원"},
{"title": "[하이헬스]탱글탱글 석류 콜라겐 젤리스틱 6+1박스(총105포)", "price": "32,900원"},
{"title": "[너트리]숯불구이맛 오징어 300g + 300g 안주 10%할인쿠폰", "price": "12,900원"},
{"title": "[폴햄](현대백화점)[폴햄] 남여 구스다운 경량 베스트 3종 택1(PHA5VP1012/PHA5VP2011/PHA5VP2012)", "price": "16,450원"},
{"title": "메이킹유 겨울신상 뽀글이/맨투맨/니트원피스/코트", "price": "9,900원"},
{"title": "[매일유업]매일두유 99.89 190ml 24팩/두유", "price": "9,900원"},
{"title": "[스마트에코]아기물티슈 모데라토 캡형 80매X20팩 엠보물티슈", "price": "14,900원"},
{"title": "폴로 하이넥 후드집업 1+1 대한민국1등 10만장돌파기념", "price": "39,900원"},
{"title": "[베지밀]베지밀 뼈에좋은 칼슘두유 검은콩 190ml 16팩 x4박스", "price": "25,900원"},
{"title": "겨울신상~70%균일가/융털/보아털/트레이닝복/패딩", "price": "19,800원"},
{"title": "갤러리아  당일손질 정광현님의 국내산 민물장어 자포니카종 1kg", "price": "29,610원"},
{"title": "노터치 파워슬라이드 청소기 1+1세트", "price": "27,430원"},
{"title": "[베베숲]아기물티슈 프리미어 캡70매 20팩", "price": "31,900원"},
{"title": "쇼인더룸 5900특가 기모맨투맨/니트/후드/빅사이즈", "price": "12,900원"},
{"title": "[백산수]백산수 2L 12병/생수전문배송", "price": "9,800원"},
{"title": "(국산) 마녀 포기김치10kg / 배추김치", "price": "29,900원"},
{"title": "[착한낙지][착한낙지] 착한낙지세트 (손질낙지 13팩+ 양념 13팩)", "price": "45,810원"},
{"title": "[맥심]화이트골드 커피믹스  160T+160T : 쿠폰가 29190원~", "price": "32,900원"},
{"title": "[크리넥스]호호바 수딩로션 미용티슈 180매 6개x2팩/각티슈 +증정", "price": "25,250원"},
{"title": "국내산 고등어 10+10팩 무료배송 팩당 70-100g", "price": "14,900원"},
{"title": "[한율]17% 쿠폰 한율 빨간쌀 철벽보습 외 (최대 50% 할인)", "price": "49,000원"},
{"title": "[프로쉬]독일 친환경 식기세척기세제 그린레몬 2개SET  60EA", "price": "22,900원"},
{"title": "[동원에프앤비]동원 통그릴비엔나 360g x 6봉", "price": "16,500원"},
{"title": "[농협] 영광 신동진쌀 총 20kg (10kg+10kg)", "price": "65,250원"},
{"title": "[푸르밀]가나초코우유190ml24팩 / 멸균우유/두유/주스/음료수", "price": "10,900원"},
{"title": "CJ프레시웨이 이츠웰부쳐스킷부채스테이크밀키트500g", "price": "10,500원"},
{"title": "스타일윙윙 여자 남자 양말 중목/발목/덧신/아동양말", "price": "6,900원"},
{"title": "소 살치살 미국200gX4팩+참소스/2세트구매시다짐육증정", "price": "20,900원"},
{"title": "[닥스]갤러리아   닥스  남여 가죽장갑 4종 택 1", "price": "28,800원"},
{"title": "[피지오겔]피지오겔 DMT 바디로션 400ml 2개 +증정", "price": "61,800원"},
{"title": "[CJ고메]고메 함박스테이크 152gx5 + 치즈함박스테이크 152gx5", "price": "22,600원"},
{"title": "(동아) 초능력6-7세 시리즈 선택구매", "price": "10,000원"},
{"title": "코코리겨울신상박스롱후드맨투맨", "price": "9,900원"},
{"title": "[아침농산]국산 농부의아침 쌀10kg  2020년산 햅쌀", "price": "29,400원"},
{"title": "[암앤해머]암앤해머 컴플리트케어 치약 178gx7개+치약 26g증정", "price": "16,900원"},
{"title": "[모나리자]데이데이비쥬 아쿠아코랄 물티슈 캡형 70매 10팩", "price": "14,900원"},
{"title": "[모나리자]모나리자 미용티슈 250매 3입 4개 총12개 각티슈 휴지", "price": "18,900원"},
{"title": "(카드15%) 2021년 EBS 초등기본서 만점왕 SET 학년별 선택 구매", "price": "41,400원"},
{"title": "스파클생수 2L 30병", "price": "12,900원"},
{"title": "[써니사이드업]신년홈트 요가레깅스/기모바지/후리스/스포츠브라", "price": "9,900원"},
{"title": "국내산 KF94 마스크 100매 개별포장 대형 식약처 인증", "price": "25,900원"},
{"title": "크레용하우스 데이비드 윌리엄스 5종세트", "price": "55,000원"},
{"title": "[좋은느낌]입는 오버나이트 L 8매X4팩/생리대/팬티형 /증정", "price": "25,310원"},
{"title": "사세 버팔로윙플러스(1kg)+버팔로스틱플러스(1kg)/ 비비수산", "price": "27,560원"},
{"title": "에스란 3~4개월+4주분/순식물성/라인자신감/매일 쏘옥", "price": "79,010원"},
{"title": "안감 기모 맨투맨 SH7613/ 라코스테", "price": "59,710원"},
{"title": "[모로칸오일]그레이트 헤어데이 세트", "price": "51,000원"},
{"title": "(행사상품)몽블랑제_온라인전용 크로와상냉동생지 120ea ", "price": "25,280원"},
{"title": "[동원에프앤비]동원산업 캐나다 자숙 랍스터 500gx3개", "price": "24,900원"},
{"title": "[오늘]현대제지 오늘 천연펄프 키친타올 125매4롤4팩 총16롤", "price": "10,900원"},
{"title": "[BYC]내의/내복/남자/남성/여자/여성/기모/겨울/발열", "price": "8,900원"},
{"title": "[페이퍼플레인]남녀공용 겨울 털신발 방한화 패딩슬립온 스니커즈", "price": "13,900원"},
{"title": "[아이러브베베]아기물티슈 아이보리 캡형 72매X20팩 엠보물티슈", "price": "19,900원"},
{"title": "1+1 밍크퍼/기모 밴딩팬츠/융털/레깅스/빅사이즈~4XL", "price": "6,900원"},
{"title": "[파스퇴르]파스퇴르 전용목장 200mL 흰 멸균우유 18입", "price": "12,900원"},
{"title": "[제주삼다수]제주삼다수 2L 12병/생수전문배송", "price": "11,900원"},
{"title": "[쟈뎅]아워티 레몬얼그레이티 500mlx24/녹차/홍차/허브차", "price": "12,900원"},
{"title": "[쏘피]볼록맞춤 슈퍼롱 오버나이트/생리대 20Px2팩+한결10P", "price": "8,900원"},
{"title": "[안다르]안다르 이태리 원사 기모 레깅스 특가", "price": "24,000원"},
{"title": "극세사 기모 넥워머/후드 워머/방한용품/목토시", "price": "4,500원"},
{"title": "[고려은단][본사직영] 비타민C 1000 600정/ 고려은단", "price": "42,150원"},
{"title": "[계림북스]계림북스 짬짬이 두뇌훈련 시리즈 4권 세트(국어력/관찰력/집중력/수학력)", "price": "28,000원"},
{"title": "[라포프] 슬림핏 기모 본딩팬츠 4종", "price": "39,000원"},
{"title": "[프롬산타]3+1 양말/롱삭스/수면 남자여자학생스니커즈덧신겨울", "price": "6,900원"},
{"title": "kf94 마스크 블랙 대형 100매 + 스트랩 1개 합리적인", "price": "39,900원"},
{"title": "[SOUP]SOUP外 베스트 상품 겨울 클리어런스 시작", "price": "34,900원"},
{"title": "홈쇼핑 남녀 겨울패딩코트 기모바지 울니트 원피스", "price": "14,900원"},
{"title": "(행사상품)[20년산]청원농협_왕의밥상_20KG 포 ", "price": "57,900원"},
{"title": "경성명과 1+1 수제 (롤케익+ 파운드케익)", "price": "10,800원"},
{"title": "(3+1) 신년맞이 균일특가 핫기모 트레이닝/융털바지", "price": "6,900원"},
{"title": "[GNM자연의품격]건조한눈엔 루테인 + 오메가3 4박스(총 4개월분)", "price": "19,900원"},
{"title": "이니스프리 새해맞이 베스트 대박 구매찬스 UP TO 50%", "price": "19,200원"},
{"title": "스탠드바닥솔+추가바닥솔", "price": "4,900원"},
{"title": "[오뚜기밥]맛있는 오뚜기밥 210g x 24개입(1박스)", "price": "19,900원"},
{"title": "[리큐]액체세탁세제 리큐 알카파워2.1Lx6개(드럼용)", "price": "18,900원"},
{"title": "[모나리자]에코모먼트 네이처 3겹 20M 30롤 3팩 롤화장지", "price": "25,900원"},
{"title": "[피지오겔]피지오겔 DMT 바디로션 400ml", "price": "30,900원"},
{"title": "아동화 노비스 (TD) (AQ9662-001)/ 나이키", "price": "39,950원"},
{"title": "매일두유 초콜릿 190ml 24팩 /우유/두유/매일", "price": "9,900원"},
{"title": "[베이비베이비]베이비베이비 아기물티슈 트윙클120매 20팩 캡형", "price": "14,900원"},
{"title": "[목우촌]목우촌 흑마늘 훈제오리 10팩", "price": "29,900원"},
{"title": "[베베앙]베베앙 아기물티슈  시그니처 대용량 100매 캡형 10팩", "price": "12,920원"},
{"title": "유니크한 패턴감각 대쿠션(솜포함) 등쿠션/바디필로우", "price": "10,900원"},
{"title": "새해 시즌마감 홈쇼핑 후드티/트레이닝/후리스/패딩", "price": "9,900원"},
{"title": "다온샵/연말특가10%/1+1/기모/청바지/슬랙스/빅사이즈", "price": "9,900원"},
{"title": "갈아만든배 340ml X24 캔", "price": "13,500원"},
{"title": "[지오다노]지오다노 신년세일 인기 푸파/경량/테리~80%OFF", "price": "39,000원"},
{"title": "[크리넥스]크리넥스 3겹 데코소프트 33MX24롤 X2팩화장지/휴지", "price": "32,900원"},
{"title": "[맥심]모카골드 커피믹스 160T+160T /쿠폰적용가30890원", "price": "34,800원"},
{"title": "[모로칸오일](공식수입원) 패밀리세트 모로칸오일 트리트먼트100ml+50ml+30ml(추가증정)", "price": "76,500원"},
{"title": "[햇반]CJ 햇반 210g 36개 (1박스)", "price": "31,900원"},
{"title": "[크리넥스]크리넥스 3겹 순수소프트화장지 27m30롤x2팩 /휴지", "price": "31,590원"},
{"title": "[퍼실]퍼실 레귤러 유니버셜 대용량 액체 세탁세제 10L", "price": "27,900원"},
{"title": "[풀무원]풀무원 토이쿠키만들기 브레드이발소 305g 3박스", "price": "34,900원"},
{"title": "[씨티지] 사가폭스 호주 양모코트", "price": "158,000원"},
{"title": "신사고 문제집 학습 기획전", "price": "14,000원"},
{"title": "수퍼맘스토리카페/팩토를 제작한 매스티안의 사고력연산 문제집/에그/EGG/선택구매", "price": "60,000원"},
{"title": "[리복][리복크로스핏] [Mens]리복 리에고 에센셜 2.0 FX0156SERIES", "price": "26,910원"},
{"title": "경북 사과 부사 5kg(26-30과내)/가정용", "price": "10,900원"},
{"title": "[비비고]비비고 사골곰탕 500g x 18개", "price": "16,740원"},
{"title": "국산/가을/겨울/아동/내복/실내복/주니어/내의/잠옷", "price": "6,900원"},
{"title": "ss무역 반반냄비 두가지 라면을 동시에", "price": "5,900원"},
{"title": "헬스브로 루테인+오메가3+종합비타민 눈영양제 4개월", "price": "19,900원"},
{"title": "로에랑스 퍼퓸 바디미스트/샤워코롱 250ml(+사은품)", "price": "6,900원"},
{"title": "[칠성사이다]칠성 사이다 210ml x 30캔", "price": "11,900원"},
{"title": "[울스포츠]울스포츠/프로스펙스 外 트레이닝복 긴바지 팬츠 모음", "price": "9,900원"},
{"title": "NEW땡큐 화장지 (30롤 x 2팩) / 3겹 두루마리 휴지", "price": "9,700원"},
{"title": "국산 KF94 마스크 100매 대형 식약처인증 개별포장", "price": "24,900원"},
{"title": "하림 버팔로 핫스파이스 윙/봉 200gX3봉", "price": "8,900원"},
{"title": "KF94 국산 순풍 마스크 100매 식약처인증 의약외품", "price": "39,900원"},
{"title": "[아비노 베이비]더멕사 아토 크림 206g 2개", "price": "21,900원"},
{"title": "[일리윤]일리윤 울트라리페어로션 528ml  2개", "price": "25,900원"},
{"title": "오늘도맛있는쌀 20kg /백미/2020년산 햅쌀", "price": "54,500원"},
{"title": "[CJ고메]고메 치즈함박스테이크 152g x10개 (냉장)", "price": "22,600원"},
{"title": "신상공개 지오송지오 21SS 기모 쉐이핑 고탄력 팬츠 4종", "price": "69,900원"},
{"title": "[길벗스쿨]길벗스쿨 기적의 유아수학 A/B/C단계 외 선택구매", "price": "39,000원"},
{"title": "[롯데푸드]롯데 의성마늘프랑크70gx10개+갈비맛프랑크70gx10개", "price": "13,900원"},
{"title": "[퐁퐁]퐁퐁 주방세제 베이킹소다 3000ML 4개", "price": "18,900원"}
]